vmk/__init__.py
vmk/combiner.py
vmk-0.0.4.dist-info/LICENSE
vmk-0.0.4.dist-info/METADATA
vmk-0.0.4.dist-info/WHEEL
vmk-0.0.4.dist-info/entry_points.txt
vmk-0.0.4.dist-info/top_level.txt
vmk-0.0.4.dist-info/RECORD
